disruptsc/__init__.py
disruptsc/main.py
disruptsc/parameters.py
disruptsc/paths.py
disruptsc/agents/__init__.py
disruptsc/agents/agent.py
disruptsc/agents/country.py
disruptsc/agents/firm.py
disruptsc/agents/household.py
disruptsc/dataprep/__init__.py
disruptsc/dataprep/admin_boundaries.py
disruptsc/disruption/__init__.py
disruptsc/disruption/disruption.py
disruptsc/model/__init__.py
disruptsc/model/basic_functions.py
disruptsc/model/builder_functions.py
disruptsc/model/caching_functions.py
disruptsc/model/check_functions.py
disruptsc/model/country_builder_functions.py
disruptsc/model/firm_builder_functions.py
disruptsc/model/household_builder_functions.py
disruptsc/model/model.py
disruptsc/model/transport_network_builder_functions.py
disruptsc/network/__init__.py
disruptsc/network/commercial_link.py
disruptsc/network/mrio.py
disruptsc/network/route.py
disruptsc/network/sc_network.py
disruptsc/network/transport_network.py
disruptsc/simulation/__init__.py
disruptsc/simulation/handling_functions.py
disruptsc/simulation/simulation.py
test/__init__.py
test/paths.py
disruptsc-1.0.6.dist-info/LICENSE
disruptsc-1.0.6.dist-info/METADATA
disruptsc-1.0.6.dist-info/WHEEL
disruptsc-1.0.6.dist-info/top_level.txt
disruptsc-1.0.6.dist-info/RECORD
