Metadata-Version: 2.1
Name: disruptsc
Version: 1.0.6
Summary: A spatial agent-based model to simulate the dynamics supply chains subject to disruptions
Home-page: https://github.com/ccolon/disruptsc
Author: Celian Colon
Author-email: celian.colon.2007@polytechnique.org
License: CC BY-NC-ND 4.0
Classifier: Programming Language :: Python :: 3
Classifier: License :: Other/Proprietary License
Classifier: Operating System :: OS Independent
Requires-Python: >=3.10, <3.11
License-File: LICENSE
Requires-Dist: geopandas==0.11.1
Requires-Dist: networkx==2.8.6
Requires-Dist: PyYAML==5.3.1
Requires-Dist: pycountry~=22.3.5
Requires-Dist: gadm~=0.0.5
